src/__init__.py
src/cli.py
src/config.py
src/database_manager.py
src/migrate.py
src/migration_generator.py
src/migration_manager.py
src/migration_runner.py
src/migrations/__init__.py
src/migrations/base_migration.py
src/migrations/m_20250320022547_user_table.py
src/migrations/m_20250322010102_create_user_table.py
john_migrator-1.2.0.dist-info/METADATA
john_migrator-1.2.0.dist-info/WHEEL
john_migrator-1.2.0.dist-info/entry_points.txt
john_migrator-1.2.0.dist-info/top_level.txt
john_migrator-1.2.0.dist-info/RECORD
