Metadata-Version: 2.4
Name: john-migrator
Version: 1.2.0
Summary: A lightweight database migration tool for Python projects
Home-page: https://github.com/Krishna-chauhan/john-migrator.git
Author: John Doe
Author-email: krishnachauhan20993@gmail.com
Project-URL: Bug Reports, https://github.com/Krishna-chauhan/john-migrator/issues
Project-URL: Source, https://github.com/Krishna-chauhan/john-migrator
Keywords: database migration sqlalchemy postgresql mysql
Classifier: Programming Language :: Python :: 3
Classifier: Programming Language :: Python :: 3.7
Classifier: Programming Language :: Python :: 3.8
Classifier: Programming Language :: Python :: 3.9
Classifier: Programming Language :: Python :: 3.10
Classifier: Programming Language :: Python :: 3.11
Classifier: Programming Language :: Python :: 3.12
Classifier: License :: OSI Approved :: MIT License
Classifier: Operating System :: OS Independent
Classifier: Development Status :: 4 - Beta
Classifier: Intended Audience :: Developers
Classifier: Topic :: Database
Classifier: Topic :: Software Development :: Libraries :: Python Modules
Requires-Python: >=3.7
Requires-Dist: sqlalchemy>=2.0.0
Requires-Dist: psycopg2-binary>=2.9.0
Requires-Dist: python-dotenv>=1.0.0
Dynamic: author
Dynamic: author-email
Dynamic: classifier
Dynamic: description
Dynamic: description-content-type
Dynamic: home-page
Dynamic: keywords
Dynamic: project-url
Dynamic: requires-dist
Dynamic: requires-python
Dynamic: summary
